{"data":{"allMarkdownRemark":{"totalCount":1,"edges":[{"node":{"fields":{"slug":"/exploration-into-serverless-backend-with-zeit","date":"2019-02-03T08:00:00.000Z"},"excerpt":"Exploration into Serverless Platform with Zeit Recently, I was reading Kent Dodd's blog post on  writing integration tests , and he casually…","timeToRead":5,"frontmatter":{"title":"Exploration into Serverless Backend with Zeit","tags":["serverless","lambda","investigation","research","backend"],"cover":"2019-02-03/zeit-co.png","date":"2019-02-03"}}}]}},"pageContext":{"tag":"backend"}}